setuptools_localimport.py
setuptools_localimport-1.0.1.dist-info/METADATA
setuptools_localimport-1.0.1.dist-info/WHEEL
setuptools_localimport-1.0.1.dist-info/top_level.txt
setuptools_localimport-1.0.1.dist-info/zip-safe
setuptools_localimport-1.0.1.dist-info/RECORD
